librecubo_super/__init__.py
librecubo_super/main.py
librecubo_super/utils.py
librecubo_super-0.0.1.dist-info/LICENSE
librecubo_super-0.0.1.dist-info/METADATA
librecubo_super-0.0.1.dist-info/WHEEL
librecubo_super-0.0.1.dist-info/RECORD
