Metadata-Version: 2.1
Name: librecubo_super
Version: 0.0.1
Summary: This is a template repository for Python projects that use Poetry for their dependency management.
Home-page: https://github.com/jfloresf/librecubo-super
Author: Jair Flores
Author-email: fjairflores17@gmail.com
Requires-Python: >=3.9,<4.0
Classifier: Programming Language :: Python :: 3
Classifier: Programming Language :: Python :: 3.9
Classifier: Programming Language :: Python :: 3.10
Classifier: Programming Language :: Python :: 3.11
Classifier: Programming Language :: Python :: 3.12
Requires-Dist: librecubo-download (>=0.0.2,<0.0.3)
Project-URL: Documentation, https://jfloresf.github.io/librecubo-super/
Project-URL: Repository, https://github.com/jfloresf/librecubo-super
